xml
<buvi>
    <model id="Res.Users" name="ResUsers" description="Users">
        <field name="Name" type="string" label="Name" required="true" translate="true"/>
        <field name="Login" type="string" label="Login" required="true" translate="true"/>
        <field name="Password" type="password" label="Password" required="true" readonly="true"/>
        <field name="GroupsId" type="Core.Group" relation="many2many" collection="true" label="Groups"/>
        <field name="Email" type="string" label="Email" translate="true"/>
        <field name="Signature" type="text" label="Signature" translate="true"/>
        <field name="Function" type="string" label="Job Title" translate="true"/>
        <field name="WorkPhone" type="string" label="Work Phone"/>
        <field name="Mobile" type="string" label="Mobile Phone"/>
        <field name="Website" type="string" label="Website"/>
        <field name="Address" type="string" label="Address"/>
        <field name="City" type="string" label="City"/>
        <field name="StateId" type="Core.State" label="State"/>
        <field name="CountryId" type="Core.Country" label="Country"/>
        <field name="Zip" type="string" label="Zip"/>
        <field name="Language" type="string" label="Language"/>
        <field name="TimeZone" type="string" label="Time Zone"/>
        <field name="Notifications" type="bool" label="Notifications"/>
        <field name="Signature" type="text" label="Signature"/>
        <field name="CompanyId" type="Res.Company" label="Company"/>
        <field name="Alias" type="string" label="Alias"/>
        <field name="PartnerId" type="Res.Partner" label="Related Partner" relation="many2one"/>
    </model>
</buvi>
